ocutils/CM_coeffs.txt
ocutils/__init__.py
ocutils/calc_SSP.py
ocutils/calc_haversine_dist.py
ocutils/calc_lat_lon.py
ocutils/calc_pressure.py
ocutils/get_path.py
ocutils/ll2wm.py
ocutils/ll2xy.py
ocutils/load_CM_coeffs.py
ocutils/pol2cart.py
ocutils/wm2ll.py
ocutils/xy2ll.py
ocutils-1.3.0.dist-info/LICENSE.txt
ocutils-1.3.0.dist-info/METADATA
ocutils-1.3.0.dist-info/WHEEL
ocutils-1.3.0.dist-info/top_level.txt
ocutils-1.3.0.dist-info/RECORD
